{
  "todos": [
    {
      "id": 1664164037849,
      "subject": "1111",
      "complete": false
    },
    {
      "id": 1664164040801,
      "subject": "11",
      "complete": false
    },
    {
      "id": 1664164042272,
      "subject": "111",
      "complete": false
    },
    {
      "id": 1664164043786,
      "subject": "11111",
      "complete": false
    },
    {
      "id": 1664164044961,
      "subject": "2222",
      "complete": false
    },
    {
      "id": 1664164046120,
      "subject": "22222",
      "complete": false
    },
    {
      "id": 1664165122223,
      "subject": "11",
      "complete": false
    },
    {
      "id": 1664165187368,
      "subject": "111",
      "complete": false
    }
  ]
}